jaanca_utils_os/__init__.py
jaanca_utils_os/utils/__init__.py
jaanca_utils_os/utils/helpers/__init__.py
jaanca_utils_os/utils/helpers/environment_parser_loader.py
jaanca_utils_os/utils/helpers/file_folder_management.py
jaanca_utils_os/utils/helpers/file_properties.py
jaanca_utils_os/utils/helpers/parse_bool.py
jaanca_utils_os/utils/helpers/parse_types.py
jaanca_utils_os-0.1.6.dist-info/LICENSE.txt
jaanca_utils_os-0.1.6.dist-info/METADATA
jaanca_utils_os-0.1.6.dist-info/WHEEL
jaanca_utils_os-0.1.6.dist-info/top_level.txt
jaanca_utils_os-0.1.6.dist-info/RECORD
