Metadata-Version: 2.1
Name: jaanca-utils-os
Version: 0.1.6
Summary: A tool library created by jaanca with operating system help functions such as reading environment variables, reading/writing files, file properties, among others.
Home-page: https://github.com/jaanca/python-libraries/tree/main/jaanca-utils-os
Author: Jaime Andres Cardona Carrillo
Author-email: jacardona@outlook.com
License: MIT License
Keywords: datetime,utc
Classifier: Development Status :: 4 - Beta
Classifier: Intended Audience :: Developers
Classifier: Intended Audience :: Information Technology
Classifier: Intended Audience :: System Administrators
Classifier: License :: OSI Approved :: MIT License
Classifier: Operating System :: OS Independent
Classifier: Programming Language :: Python :: 3.10
Classifier: Programming Language :: Python :: 3.11
Classifier: Programming Language :: Python :: 3.8
Classifier: Programming Language :: Python :: 3.9
Classifier: Programming Language :: Python :: 3
Classifier: Programming Language :: Python
Classifier: Topic :: Software Development :: Libraries :: Python Modules
Classifier: Topic :: System :: Monitoring
Classifier: Topic :: Software Development
Classifier: Typing :: Typed
Requires-Python: >=3.8
License-File: LICENSE.txt
Provides-Extra: dotenv
Requires-Dist: python-dotenv >=1.0.0 ; extra == 'dotenv'
